flaskdemo-1.0.0.dist-info/METADATA
flaskdemo-1.0.0.dist-info/RECORD
flaskdemo-1.0.0.dist-info/WHEEL
flaskdemo-1.0.0.dist-info/top_level.txt
views/__init__.py
views/index/__init__.py
views/index/index_router.py
views/user/__init__.py
views/user/user_router.py
